LICENSE
MANIFEST.in
README.rst
setup.py
django_mailfactory_extras.egg-info/PKG-INFO
django_mailfactory_extras.egg-info/SOURCES.txt
django_mailfactory_extras.egg-info/dependency_links.txt
django_mailfactory_extras.egg-info/not-zip-safe
django_mailfactory_extras.egg-info/requires.txt
django_mailfactory_extras.egg-info/top_level.txt
mailfactory_extras/__init__.py
mailfactory_extras/__init__.pyc
mailfactory_extras/apps.py
mailfactory_extras/smsfactory.py
mailfactory_extras/smsfactory.pyc
mailfactory_extras/utils.py
mailfactory_extras/.ropeproject/config.py
mailfactory_extras/.ropeproject/globalnames
mailfactory_extras/.ropeproject/history
mailfactory_extras/.ropeproject/objectdb
mailfactory_extras/__pycache__/__init__.cpython-34.pyc
mailfactory_extras/__pycache__/smsfactory.cpython-34.pyc
mailfactory_extras/mails/__init__.py
mailfactory_extras/mails/backends/__init__.py
mailfactory_extras/mails/backends/celery/__init__.py
mailfactory_extras/mails/backends/celery/mails.py
mailfactory_extras/mails/backends/celery/messages.py
mailfactory_extras/mails/backends/celery/.ropeproject/config.py
mailfactory_extras/mails/backends/celery/.ropeproject/globalnames
mailfactory_extras/mails/backends/celery/.ropeproject/history
mailfactory_extras/mails/backends/celery/.ropeproject/objectdb
mailfactory_extras/sms/__init__.py
mailfactory_extras/sms/__init__.pyc
mailfactory_extras/sms/base.py
mailfactory_extras/sms/base.pyc
mailfactory_extras/sms/.ropeproject/config.py
mailfactory_extras/sms/.ropeproject/globalnames
mailfactory_extras/sms/.ropeproject/history
mailfactory_extras/sms/.ropeproject/objectdb
mailfactory_extras/sms/twilio/__init__.py
mailfactory_extras/sms/twilio/__init__.pyc
mailfactory_extras/sms/twilio/sms.py
mailfactory_extras/sms/twilio/sms.pyc
mailfactory_extras/sms/twilio/.ropeproject/config.py
mailfactory_extras/sms/twilio/.ropeproject/globalnames
mailfactory_extras/sms/twilio/.ropeproject/history
mailfactory_extras/sms/twilio/.ropeproject/objectdb
mailfactory_extras/templates/mailfactory_extras/form.html
mailfactory_extras/templates/mailfactory_extras/list.html
mailfactory_extras/templates/mailfactory_extras/preview_message.html