Metadata-Version: 1.0
Name: django-mailfactory-extras
Version: 0.25
Summary: Extensions for django-mail-factory, like django-xadmin integration or asynchronous message sending
Home-page: https://github.com/jneight/django-mailfactory-extras
Author: Javier Cordero
Author-email: jcorderomartinez@gmail.com
License: Apache 2.0
Platform: UNKNOWN
